gaspype/__init__.py
gaspype/_main.py
gaspype/_operations.py
gaspype/_phys_data.py
gaspype/_solver.py
gaspype/constants.py
gaspype/gas_systems.py
gaspype/membrane.py
gaspype/py.typed
gaspype/typing.py
gaspype/units.py
gaspype/data/therm_data.bin
gaspype-1.1.3.dist-info/licenses/LICENSE
gaspype-1.1.3.dist-info/METADATA
gaspype-1.1.3.dist-info/WHEEL
gaspype-1.1.3.dist-info/top_level.txt
gaspype-1.1.3.dist-info/RECORD
