Metadata-Version: 2.4
Name: gaspype
Version: 1.1.3
Summary: Performant library for thermodynamic calculations
Author-email: Nicolas Kruse <nicolas.kruse@dlr.de>
License-Expression: MIT
Project-URL: Homepage, https://dlr-institute-of-future-fuels.github.io/gaspype/
Project-URL: documentation, https://dlr-institute-of-future-fuels.github.io/gaspype/api/
Project-URL: Repository, https://github.com/DLR-Institute-of-Future-Fuels/gaspype.git
Project-URL: Issues, https://github.com/DLR-Institute-of-Future-Fuels/gaspype/issues
Classifier: Programming Language :: Python :: 3
Classifier: Operating System :: OS Independent
Requires-Python: >=3.10
License-File: LICENSE
Requires-Dist: numpy>2.0.0
Requires-Dist: scipy>1.12.0
Provides-Extra: dev
Requires-Dist: flake8; extra == "dev"
Requires-Dist: mypy; extra == "dev"
Requires-Dist: pytest; extra == "dev"
Requires-Dist: pandas; extra == "dev"
Requires-Dist: cantera; extra == "dev"
Requires-Dist: pyyaml>=6.0.1; extra == "dev"
Requires-Dist: types-PyYAML; extra == "dev"
Requires-Dist: scipy-stubs; extra == "dev"
Requires-Dist: matplotlib; extra == "dev"
Provides-Extra: doc-build
Requires-Dist: sphinx; extra == "doc-build"
Requires-Dist: pydata_sphinx_theme; extra == "doc-build"
Requires-Dist: sphinx-autodoc-typehints; extra == "doc-build"
Requires-Dist: myst-parser; extra == "doc-build"
Requires-Dist: pandas; extra == "doc-build"
Requires-Dist: matplotlib; extra == "doc-build"
Requires-Dist: ipykernel; extra == "doc-build"
Requires-Dist: jupyter; extra == "doc-build"
Requires-Dist: nbconvert; extra == "doc-build"
Requires-Dist: notedown; extra == "doc-build"
Dynamic: license-file
